aa_killstory/__init__.py
aa_killstory/admin.py
aa_killstory/apps.py
aa_killstory/hooks.py
aa_killstory/models.py
aa_killstory/urls.py
aa_killstory/views.py
aa_killstory/migrations/__init__.py
aa_killstory/static/aa_killstory/css/style.css
aa_killstory/templates/aa_killstory/base.html
killstory/__init__.py
killstory/admin.py
killstory/apps.py
killstory/hooks.py
killstory/models.py
killstory/urls.py
killstory/views.py
killstory/management/__init__.py
killstory/management/commands/__init__.py
killstory/management/commands/populate_kills.py
killstory/migrations/__init__.py
killstory/static/aa_killstory/css/style.css
killstory/templates/aa_killstory/base.html
aa_killstory-0.1.1.8.dist-info/LICENSE
aa_killstory-0.1.1.8.dist-info/METADATA
aa_killstory-0.1.1.8.dist-info/WHEEL
aa_killstory-0.1.1.8.dist-info/top_level.txt
aa_killstory-0.1.1.8.dist-info/RECORD
