Metadata-Version: 2.1
Name: aa-killstory
Version: 0.1.1.8
Summary: A plugin for Alliance Auth to manage kill stories.
Home-page: https://github.com/Erkaek/aa-killstory
Author: Erkaek
Author-email: erkaekanon@outlook.com
License: MIT License
Platform: UNKNOWN
Classifier: Environment :: Web Environment
Classifier: Framework :: Django
Classifier: Intended Audience :: Developers
Classifier: License :: OSI Approved :: MIT License
Classifier: Operating System :: OS Independent
Classifier: Programming Language :: Python :: 3
License-File: LICENSE
Requires-Dist: django >=3.2
Requires-Dist: requests
